websites_metrics_collector/__init__.py
websites_metrics_collector/main.py
websites_metrics_collector/classes/Driver.py
websites_metrics_collector/classes/__init__.py
websites_metrics_collector/communication/__init__.py
websites_metrics_collector/communication/webpages_fetcher.py
websites_metrics_collector/configuration/__init__.py
websites_metrics_collector/helpers/__init__.py
websites_metrics_collector/helpers/regex_functions.py
websites_metrics_collector-0.0.1.dist-info/LICENSE
websites_metrics_collector-0.0.1.dist-info/METADATA
websites_metrics_collector-0.0.1.dist-info/WHEEL
websites_metrics_collector-0.0.1.dist-info/top_level.txt
websites_metrics_collector-0.0.1.dist-info/RECORD
