Metadata-Version: 2.1
Name: websites-metrics-collector
Version: 0.0.1
Summary: An application that collects metrics from websites and produce results as messages to Kafka
Home-page: https://github.com/antoniodimariano/websites_metrics_collector
Author: Antonio Di Mariano
Author-email: antonio.dimariano@gmail.com
License: License :: OSI Approved :: Apache Software License
Platform: UNKNOWN
Classifier: Programming Language :: Python :: 3
Classifier: License :: OSI Approved :: Apache Software License
Classifier: Operating System :: OS Independent
Requires-Python: >=3.6
License-File: LICENSE
Requires-Dist: requests
Requires-Dist: confluent-kafka-producers-wrapper
Requires-Dist: aiohttp
